csvtodb/Column.py
csvtodb/Csv.py
csvtodb/Database.py
csvtodb/Laravel.py
csvtodb/LaravelColumn.py
csvtodb/LaravelTable.py
csvtodb/Mysql.py
csvtodb/MysqlColumn.py
csvtodb/MysqlDb.py
csvtodb/MysqlTable.py
csvtodb/Table.py
csvtodb/__init__.py
csvtodb-1.1.2.dist-info/License.txt
csvtodb-1.1.2.dist-info/METADATA
csvtodb-1.1.2.dist-info/WHEEL
csvtodb-1.1.2.dist-info/top_level.txt
csvtodb-1.1.2.dist-info/RECORD
