Metadata-Version: 2.1
Name: csvtodb
Version: 1.1.2
Summary: Make it easier to build database/table/seeders for DBMS or framework like laravel
Home-page: https://github.com/akk0ga/CsvToDB
Author: akk0ga
Author-email: ttn.glock@orange.fr
License: UNKNOWN
Keywords: csv,db,database,sql,framework,mysql
Platform: UNKNOWN
Classifier: Programming Language :: Python :: 3.9
Classifier: License :: OSI Approved :: MIT License
Classifier: Intended Audience :: Developers
Classifier: Operating System :: Unix
Classifier: Operating System :: MacOS :: MacOS X
Classifier: Operating System :: Microsoft :: Windows
Requires-Python: >=3.6
License-File: License.txt
